jentic-0.9.5.dist-info/METADATA
jentic-0.9.5.dist-info/WHEEL
jentic-0.9.5.dist-info/entry_points.txt
jentic-0.9.5.dist-info/licenses/LICENSE
jentic-0.9.5.dist-info/licenses/NOTICE
jentic/__init__.py
jentic/jentic.py
jentic/lib/__init__.py
jentic/lib/agent_runtime/__init__.py
jentic/lib/agent_runtime/agent_tools.py
jentic/lib/agent_runtime/api_cache.py
jentic/lib/agent_runtime/api_hub.py
jentic/lib/agent_runtime/config.py
jentic/lib/agent_runtime/tool_execution.py
jentic/lib/agent_runtime/tool_specs.py
jentic/lib/cfg.py
jentic/lib/core_api.py
jentic/lib/exc.py
jentic/lib/models.py
jentic-0.9.5.dist-info/RECORD
