Metadata-Version: 2.4
Name: jentic
Version: 0.9.5
Summary: Jentic SDK for the discovery and execution of APIs and workflows
Author-Email: Jentic <hello@jentic.com>
License-Expression: Apache-2.0
License-File: LICENSE
License-File: NOTICE
Classifier: Development Status :: 4 - Beta
Classifier: Programming Language :: Python :: 3
Requires-Python: >=3.11
Requires-Dist: arazzo-runner>=0.9.2
Requires-Dist: pydantic>=2.0.0
Requires-Dist: httpx>=0.28.1
Requires-Dist: tenacity>=9.1.2
